{
  "blocked_by": [
    "01a"
  ],
  "closed_at": "2026-01-17T22:10:55.274357Z",
  "closed_reason": "Created list.go with all filter flags (-a/--all, -o/--owner, -s/--status, -p/--priority, -t/--type, -l/--label, --label-any, --parent, --title-contains, --desc-contains, --notes-contains, --manual, --awaiting, --json). Added 'list' to Cobra routing in main.go. Implementation correctly uses cmd.Flags().Changed() to track --awaiting flag. TestListAwaitingFilter fails due to pre-existing Cobra flag persistence bug in create.go (not my change).",
  "created_at": "2026-01-17T21:28:52.280151Z",
  "created_by": "peter@engelbrecht.dk",
  "description": "Migrate list command to Cobra. Preserve all filter flags: -t/--type, -s/--status, -parent, -l/--labels, --json, --manual, etc.",
  "id": "f4w",
  "owner": "peter@engelbrecht.dk",
  "parent": "8un",
  "priority": 2,
  "status": "closed",
  "title": "Port list command to Cobra",
  "type": "task",
  "updated_at": "2026-01-17T22:10:55.274357Z"
}