{
  "closed_at": "2026-01-16T19:52:18.621842Z",
  "closed_reason": "Added dedicated 'Human-Only Tasks (awaiting=work)' section to tk top-level help with clear explanation and examples for creating/updating tasks with --awaiting work, how they're skipped by agent queues, and how to return them to agent queue",
  "created_at": "2026-01-16T17:41:16.310145Z",
  "created_by": "peter@engelbrecht.dk",
  "description": "The tk top-level help mentions --manual is deprecated but doesn't explain --awaiting=work as the replacement. Add clear documentation for awaiting=work usage.",
  "id": "uxj",
  "owner": "peter@engelbrecht.dk",
  "priority": 3,
  "status": "closed",
  "title": "Document awaiting=work in tk top-level help",
  "type": "task",
  "updated_at": "2026-01-16T19:52:18.621842Z"
}